codicon/__init__.py
codicon/archivus.py
codicon/common.py
codicon/gods.py
codicon/graphos.py
codicon/logos.py
codicon/machina.py
codicon/segfalux.py
codicon/void.py
pycodicon-0.1.3.dist-info/licenses/LICENSE
pycodicon-0.1.3.dist-info/METADATA
pycodicon-0.1.3.dist-info/WHEEL
pycodicon-0.1.3.dist-info/top_level.txt
pycodicon-0.1.3.dist-info/RECORD
