Metadata-Version: 2.4
Name: pycodicon
Version: 0.1.3
Summary: Python tools to sacrifice to the Codicon.
Author-email: redisnotblue <ededmaude@gmail.com>
Project-URL: Homepage, https://github.com/redisnotbluedev/codicon
Project-URL: Issues, https://github.com/redisnotbluedev/codicon/issues
Requires-Python: >=3.8
License-File: LICENSE
Requires-Dist: pyyaml
Requires-Dist: moderngl
Requires-Dist: numpy
Dynamic: license-file
